novel_dl/__init__.py
novel_dl/info.py
novel_dl/main.py
novel_dl/option.py
novel_dl/utils.py
novel_dl/downloader/__init__.py
novel_dl/downloader/default.py
novel_dl/downloader/__pycache__/__init__.cpython-310.pyc
novel_dl/downloader/__pycache__/default.cpython-310.pyc
novel_dl/themes/kakuyomu/.gitattributes
novel_dl/themes/kakuyomu/base.html
novel_dl/themes/kakuyomu/config.json
novel_dl/themes/kakuyomu/index.html
novel_dl/themes/kakuyomu/single.html
novel_dl/themes/kakuyomu/static/app-256.png
novel_dl/themes/kakuyomu/static/custom.css
novel_dl/themes/kakuyomu/static/custom.js
novel_dl/themes/kakuyomu/static/dcicons-regular.eot
novel_dl/themes/kakuyomu/static/dcicons-regular.otf
novel_dl/themes/kakuyomu/static/dcsymbols-regular.otf
novel_dl/themes/kakuyomu/static/dcsymbols-regular.woff
novel_dl/themes/kakuyomu/static/favicon.ico
novel_dl/themes/kakuyomu/static/ios-60.png
novel_dl/themes/kakuyomu/static/kakuyomu-logo-vertical-white.png
novel_dl/themes/kakuyomu/static/kakuyomu-logo-vertical.png
novel_dl/themes/kakuyomu/static/kakuyomu-logo-white.png
novel_dl/themes/kakuyomu/static/kakuyomu-logo.png
novel_dl/themes/kakuyomu/static/kakuyomu.css
novel_dl/themes/kakuyomu/static/kakuyomu.js
novel_dl/themes/kakuyomu/static/switch.css
novel_dl/themes/kakuyomu/static/switch.js
novel_dl/themes/kakuyomu/tool/css_setup.sh
novel_dl/themes/kakuyomu/tool/custom.css
novel_dl/themes/kakuyomu/tool/index.html
novel_dl/themes/kakuyomu/tool/template.html
novel_dl/themes/narou/.gitattributes
novel_dl/themes/narou/base.html
novel_dl/themes/narou/base_body_mobile.html
novel_dl/themes/narou/base_body_pc.html
novel_dl/themes/narou/base_mobile.html
novel_dl/themes/narou/base_pc.html
novel_dl/themes/narou/config.json
novel_dl/themes/narou/index.html
novel_dl/themes/narou/index_body_mobile.html
novel_dl/themes/narou/index_body_pc.html
novel_dl/themes/narou/index_mobile.html
novel_dl/themes/narou/index_pc.html
novel_dl/themes/narou/single.html
novel_dl/themes/narou/single_mobile.html
novel_dl-1.6.2.dist-info/LICENSE
novel_dl-1.6.2.dist-info/METADATA
novel_dl-1.6.2.dist-info/WHEEL
novel_dl-1.6.2.dist-info/entry_points.txt
novel_dl-1.6.2.dist-info/top_level.txt
novel_dl-1.6.2.dist-info/RECORD
