Metadata-Version: 2.1
Name: novel-dl
Version: 1.6.2
Summary: Novel downloader
Home-page: https://github.com/Keinsleif/novel-dl
Author: Kondo Kazuto
Author-email: mountaindull@gmail.com
License: MIT License
Classifier: Environment :: Console
Classifier: License :: OSI Approved :: MIT License
Classifier: Natural Language :: Japanese
Classifier: Natural Language :: English
Classifier: Operating System :: Unix
Classifier: Programming Language :: Python :: 3 :: Only
License-File: LICENSE
Requires-Dist: beautifulsoup4
Requires-Dist: Jinja2
Requires-Dist: pytz
Requires-Dist: requests
Requires-Dist: tqdm
